spoks/Spoks.py
spoks/__init__.py
spoks/data/adjective.json
spoks/data/aspek.json
spoks/data/aspek2.json
spoks/data/kategori.json
PySpoks-0.0.4.dist-info/LICENCE
PySpoks-0.0.4.dist-info/METADATA
PySpoks-0.0.4.dist-info/WHEEL
PySpoks-0.0.4.dist-info/top_level.txt
PySpoks-0.0.4.dist-info/RECORD
