Metadata-Version: 2.1
Name: PySpoks
Version: 0.0.4
Summary: Sistem Pemeringkat Otomatis Berbasis Kata Sifat
Home-page: https://github.com/ElfanRodh/PySpoks
Author: ElfanRodh
Author-email: elfanapoywali@gmail.com
License: UNKNOWN
Platform: UNKNOWN
Classifier: Programming Language :: Python :: 3
Classifier: License :: OSI Approved :: MIT License
Classifier: Operating System :: OS Independent
